MANIFEST.in
setup.py
remote_run.egg-info/PKG-INFO
remote_run.egg-info/SOURCES.txt
remote_run.egg-info/dependency_links.txt
remote_run.egg-info/entry_points.txt
remote_run.egg-info/requires.txt
remote_run.egg-info/top_level.txt
remoterun/.remoterunignore
remoterun/.remoterunrc
remoterun/__init__.py
remoterun/__main__.py
remoterun/remoterun.py
remoterun/utils.py
test/test_nargs.py
test/test_nargs_app.py
test/test_remoterun.py
test/test_utils.py