Metadata-Version: 1.0
Name: remote-run
Version: 0.6
Summary: Running your script on a remote machine as if it were on your local one
Home-page: https://github.com/phizaz/remote-run
Author: Konpat Preechakul
Author-email: the.akita.ta@gmail.com
License: UNKNOWN
Keywords: remote,utility
Platform: UNKNOWN
